mcp_overkiz/__init__.py
mcp_overkiz/server.py
mcp_overkiz-0.1.2.dist-info/METADATA
mcp_overkiz-0.1.2.dist-info/WHEEL
mcp_overkiz-0.1.2.dist-info/entry_points.txt
mcp_overkiz-0.1.2.dist-info/RECORD
