Metadata-Version: 2.4
Name: mcp-overkiz
Version: 0.1.2
Summary: MCP server for controlling lights using overkiz
Author-email: Eric Marchand <eric.marchand.n7@gmail.com>
Requires-Python: >=3.13.3
Requires-Dist: mcp>=1.7.1
Requires-Dist: pyoverkiz>=1.1.0
